Lattice_Scripts/0c61af02-51eb-402b-afe9-2a1c0cafb88b.gv
Lattice_Scripts/0c61af02-51eb-402b-afe9-2a1c0cafb88b.gv.pdf
Lattice_Scripts/22aba17d-0803-40d1-a6d7-f5526b847a82.gv
Lattice_Scripts/22aba17d-0803-40d1-a6d7-f5526b847a82.gv.pdf
Lattice_Scripts/3202f283-fd53-489f-a524-6c2fd4eb742a.gv
Lattice_Scripts/3202f283-fd53-489f-a524-6c2fd4eb742a.gv.pdf
Lattice_Scripts/40861fca-41e9-4582-8ebf-fb5f53177aa2
Lattice_Scripts/420099d8-e96d-4900-9fe7-b952495b28c0
Lattice_Scripts/5ee8c02a-4299-4464-9406-c91d7596a3df.gv
Lattice_Scripts/5ee8c02a-4299-4464-9406-c91d7596a3df.gv.pdf
Lattice_Scripts/6243ae9e-b9ca-4301-bc1b-23820b5b5c67.gv
Lattice_Scripts/6243ae9e-b9ca-4301-bc1b-23820b5b5c67.gv.pdf
Lattice_Scripts/7101765c-cde4-4086-a6cf-85ca9f573d33.gv
Lattice_Scripts/7101765c-cde4-4086-a6cf-85ca9f573d33.gv.pdf
Lattice_Scripts/80d5097d-a203-4423-9177-8db54d9ff8cc.gv
Lattice_Scripts/80d5097d-a203-4423-9177-8db54d9ff8cc.gv.pdf
Lattice_Scripts/8558953d-ec61-4d46-ab51-cad78015e389.gv
Lattice_Scripts/8558953d-ec61-4d46-ab51-cad78015e389.gv.pdf
Lattice_Scripts/9167244b-dc36-488e-9a24-8c0f207c3aaa.gv
Lattice_Scripts/9167244b-dc36-488e-9a24-8c0f207c3aaa.gv.pdf
Lattice_Scripts/91f695f0-ac92-403e-81d8-f7d76a5a6eba.gv
Lattice_Scripts/91f695f0-ac92-403e-81d8-f7d76a5a6eba.gv.pdf
Lattice_Scripts/9d8f8c6d-22ed-4a7e-af45-8ac72691f52c.gv
Lattice_Scripts/9d8f8c6d-22ed-4a7e-af45-8ac72691f52c.gv.pdf
Lattice_Scripts/__init__.py
Lattice_Scripts/a972d228-3f01-42fc-89e8-b0431bcd87b6.gv
Lattice_Scripts/a972d228-3f01-42fc-89e8-b0431bcd87b6.gv.pdf
Lattice_Scripts/bb_tree.py
Lattice_Scripts/ce8e0387-b735-400d-a303-cc56e4769a9b.gv
Lattice_Scripts/ce8e0387-b735-400d-a303-cc56e4769a9b.gv.pdf
Lattice_Scripts/d962d2ca-0365-46f3-9b0e-3c07645b036d.gv
Lattice_Scripts/d962d2ca-0365-46f3-9b0e-3c07645b036d.gv.pdf
Lattice_Scripts/dot_output/124ce352-4606-4b8e-83cf-894a431e02f5.gv
Lattice_Scripts/dot_output/124ce352-4606-4b8e-83cf-894a431e02f5.gv.pdf
Lattice_Scripts/dot_output/18839347-7fff-4bf6-b283-22b194da1d73.gv
Lattice_Graph_Manipulation-1.4.0.dist-info/WHEEL
Lattice_Graph_Manipulation-1.4.0.dist-info/METADATA
Lattice_Graph_Manipulation-1.4.0.dist-info/licenses/LICENSE
Lattice_Graph_Manipulation-1.4.0.dist-info/RECORD
