Metadata-Version: 2.1
Name: Lattice-Graph-Manipulation
Version: 1.4.0
License: MIT
Author-email: MII <mnel.jnr@gmail.com>
Requires-Python: >=3.9
Requires-Dist: graphviz>=0.20.1
